{
    "title": "Pork, Sage and Onion Stuffing Recipe | Marco Pierre White",
    "description": "Watch Chef Marco Pierre White put together this classic pork sage and onion recipe. An easy recipe from Knorr. This traditional stuffing recipe is intended t...",
    "referenceId": null,
    "date_created": "1393054142",
    "date_modified": "1418181164",
    "tags": "",
    "sourceId": "4",
    "VIDEO_LENGTH": "LONG",
    "status": "approved",
    "visibility": "1",
    "id": "143674",
    "loginId": "3",
    "entityType": "1",
    "titleTextEncoded": "Pork-Sage-and-Onion-Stuffing-Recipe-Marco-Pierre-White",
    "category": null,
    "duration": 248,
    "settings": [],
    "asset": {
        "author": "KnorrRecipes",
        "videoId": "N26DvrMjv5g",
        "hookText": "Watch Chef Marco Pierre White put together this classic pork sage and onion recipe. An easy recipe from Knorr. This traditional stuffing recipe is intended t...",
        "thumbnailUrl": "https:\/\/i.ytimg.com\/vi\/N26DvrMjv5g\/hqdefault.jpg",
        "mediaDuration": "248",
        "hdvFlag": 0,
        "uploadDate": 1292452600,
        "prettyDuration": "04:08"
    },
    "transcripts": null,
    "VV_VI": null,
    "CVV_VI": null,
    "engagement_score": null,
    "conversion_score": null,
    "metrics_statistics": null,
    "tvp_profiles": [
        "18"
    ],
    "tvp_profiles_manual": null,
    "tvp_profiles_maxscore": 291.56104
}