{
    "title": "Chicken Broth Recipe | Marco Pierre White",
    "description": "Watch Chef Marco Pierre White as he shows how to make a simple but sumptuous chicken broth recipe. An easy recipe from Knorr. This rich golden chicken broth ...",
    "referenceId": null,
    "date_created": "1393054138",
    "date_modified": "1418181163",
    "tags": "",
    "sourceId": "4",
    "VIDEO_LENGTH": "LONG",
    "status": "approved",
    "visibility": "1",
    "id": "143634",
    "loginId": "3",
    "entityType": "1",
    "titleTextEncoded": "Chicken-Broth-Recipe-Marco-Pierre-White",
    "category": null,
    "duration": 321,
    "settings": [],
    "asset": {
        "author": "KnorrRecipes",
        "videoId": "oGAu_PHxPQc",
        "hookText": "Watch Chef Marco Pierre White as he shows how to make a simple but sumptuous chicken broth recipe. An easy recipe from Knorr. This rich golden chicken broth ...",
        "thumbnailUrl": "https:\/\/i.ytimg.com\/vi\/oGAu_PHxPQc\/hqdefault.jpg",
        "mediaDuration": "321",
        "hdvFlag": 0,
        "uploadDate": 1294358326,
        "prettyDuration": "05:21"
    },
    "transcripts": null,
    "VV_VI": null,
    "CVV_VI": null,
    "engagement_score": null,
    "conversion_score": null,
    "metrics_statistics": null,
    "tvp_profiles": [
        "11"
    ],
    "tvp_profiles_manual": null,
    "tvp_profiles_maxscore": 393.267
}