{
    "title": "A Day in the Life with Alison Sweeney - Presented By Petco",
    "description": "Subscribe to our channel: http:\/\/bit.ly\/12dY9oO Biggest Loser host and pet lover Alison Sweeney and her dog Winky show you how eating right and staying activ...",
    "referenceId": null,
    "date_created": "1394762648",
    "date_modified": "1418181182",
    "tags": "",
    "sourceId": "4",
    "VIDEO_LENGTH": "SHORT",
    "status": "approved",
    "visibility": "1",
    "id": "145388",
    "loginId": "3",
    "entityType": "1",
    "titleTextEncoded": "A-Day-in-the-Life-with-Alison-Sweeney-Presented-By-Petco",
    "category": null,
    "duration": 88,
    "settings": [],
    "asset": {
        "author": "Petco",
        "videoId": "_jXFNVWAyxY",
        "hookText": "Subscribe to our channel: http:\/\/bit.ly\/12dY9oO Biggest Loser host and pet lover Alison Sweeney and her dog Winky show you how eating right and staying activ...",
        "thumbnailUrl": "https:\/\/i.ytimg.com\/vi\/_jXFNVWAyxY\/maxresdefault.jpg",
        "mediaDuration": "88",
        "hdvFlag": 1,
        "uploadDate": 1327648890,
        "prettyDuration": "01:28"
    },
    "transcripts": null,
    "VV_VI": null,
    "CVV_VI": null,
    "engagement_score": null,
    "conversion_score": null,
    "metrics_statistics": null,
    "tvp_profiles": [
        "18",
        "14"
    ],
    "tvp_profiles_manual": null,
    "tvp_profiles_maxscore": 797.05676
}