{
    "title": "Sofia Ribeiro is all in",
    "description": "Uma jovem actriz com um talento ineg\u00e1vel: Sofia Ribeiro. A embaixadora da adidas em Portugal gravou um v\u00eddeo para a marca no qual conta como chegou ao mundo ...",
    "referenceId": null,
    "date_created": "1396646910",
    "date_modified": "1418181259",
    "tags": "",
    "sourceId": "4",
    "VIDEO_LENGTH": "SHORT",
    "status": "approved",
    "visibility": "1",
    "id": "151128",
    "loginId": "3",
    "entityType": "1",
    "titleTextEncoded": "Sofia-Ribeiro-is-all-in",
    "category": null,
    "duration": 149,
    "settings": [],
    "asset": {
        "author": "adidas",
        "videoId": "vIq3fQyJ9nE",
        "hookText": "Uma jovem actriz com um talento ineg\u00e1vel: Sofia Ribeiro. A embaixadora da adidas em Portugal gravou um v\u00eddeo para a marca no qual conta como chegou ao mundo ...",
        "thumbnailUrl": "https:\/\/i.ytimg.com\/vi\/vIq3fQyJ9nE\/maxresdefault.jpg",
        "mediaDuration": "149",
        "hdvFlag": 1,
        "uploadDate": 1313710688,
        "prettyDuration": "02:29"
    },
    "transcripts": null,
    "VV_VI": null,
    "CVV_VI": null,
    "engagement_score": null,
    "conversion_score": null,
    "metrics_statistics": null,
    "tvp_profiles": [
        "18"
    ],
    "tvp_profiles_manual": null,
    "tvp_profiles_maxscore": 283.02274
}