{
    "title": "Tilly's Takes On The US Open of Surfing 2012",
    "description": "This Summer, we hit up the US Open hard with our Tilly's Booth on the sand and on the street. Check out the good times we had!",
    "referenceId": null,
    "date_created": "1397072630",
    "date_modified": "1418181274",
    "tags": "",
    "sourceId": "4",
    "VIDEO_LENGTH": "SHORT",
    "status": "approved",
    "visibility": "1",
    "id": "151972",
    "loginId": "3",
    "entityType": "1",
    "titleTextEncoded": "Tilly-s-Takes-On-The-US-Open-of-Surfing-2012",
    "category": null,
    "duration": 115,
    "settings": [],
    "asset": {
        "author": "tillys",
        "videoId": "4OLTQ1qfIKI",
        "hookText": "This Summer, we hit up the US Open hard with our Tilly's Booth on the sand and on the street. Check out the good times we had!",
        "thumbnailUrl": "https:\/\/i.ytimg.com\/vi\/4OLTQ1qfIKI\/maxresdefault.jpg",
        "mediaDuration": "115",
        "hdvFlag": 1,
        "uploadDate": 1349335681,
        "prettyDuration": "01:55"
    },
    "transcripts": null,
    "VV_VI": null,
    "CVV_VI": null,
    "engagement_score": null,
    "conversion_score": null,
    "metrics_statistics": null,
    "tvp_profiles": [
        "19",
        "16"
    ],
    "tvp_profiles_manual": null,
    "tvp_profiles_maxscore": 8331.53
}