{
    "title": "Yelawolf Talks his FMS Country Fresh line",
    "description": "Yelawolf skates through the streets and breaks down his second season of his Famous Stars & Straps signature line, Country Fresh.",
    "referenceId": null,
    "date_created": "1397072630",
    "date_modified": "1418181274",
    "tags": "",
    "sourceId": "4",
    "VIDEO_LENGTH": "SHORT",
    "status": "approved",
    "visibility": "1",
    "id": "151966",
    "loginId": "3",
    "entityType": "1",
    "titleTextEncoded": "Yelawolf-Talks-his-FMS-Country-Fresh-line",
    "category": null,
    "duration": 103,
    "settings": [],
    "asset": {
        "author": "tillys",
        "videoId": "IzmaZJffz5M",
        "hookText": "Yelawolf skates through the streets and breaks down his second season of his Famous Stars & Straps signature line, Country Fresh.",
        "thumbnailUrl": "https:\/\/i.ytimg.com\/vi\/IzmaZJffz5M\/maxresdefault.jpg",
        "mediaDuration": "103",
        "hdvFlag": 1,
        "uploadDate": 1352446796,
        "prettyDuration": "01:43"
    },
    "transcripts": null,
    "VV_VI": null,
    "CVV_VI": null,
    "engagement_score": null,
    "conversion_score": null,
    "metrics_statistics": null,
    "tvp_profiles": [
        "26",
        "22",
        "25"
    ],
    "tvp_profiles_manual": null,
    "tvp_profiles_maxscore": 198.1205
}