{
    "title": "adidas is all in -- 30 Rose Edition",
    "description": "Heart over head. Inclusion over ego. United by passion, we go all in. Go all in at http:\/\/www.youtube.com\/adidas to see more. Music is \"Civilization\" from th...",
    "referenceId": null,
    "date_created": "1398106921",
    "date_modified": "1418181309",
    "tags": "",
    "sourceId": "4",
    "VIDEO_LENGTH": "SHORT",
    "status": "approved",
    "visibility": "1",
    "id": "154810",
    "loginId": "3",
    "entityType": "1",
    "titleTextEncoded": "adidas-is-all-in-30-Rose-Edition",
    "category": null,
    "duration": 31,
    "settings": [],
    "asset": {
        "author": "adidas",
        "videoId": "uSCbBReatVs",
        "hookText": "Heart over head. Inclusion over ego. United by passion, we go all in. Go all in at http:\/\/www.youtube.com\/adidas to see more. Music is \"Civilization\" from th...",
        "thumbnailUrl": "https:\/\/i.ytimg.com\/vi\/uSCbBReatVs\/maxresdefault.jpg",
        "mediaDuration": "31",
        "hdvFlag": 1,
        "uploadDate": 1299888904,
        "prettyDuration": "00:31"
    },
    "transcripts": null,
    "VV_VI": null,
    "CVV_VI": null,
    "engagement_score": null,
    "conversion_score": null,
    "metrics_statistics": null,
    "tvp_profiles": [
        "7",
        "12",
        "26"
    ],
    "tvp_profiles_manual": null,
    "tvp_profiles_maxscore": 3175.0461
}