{
    "title": "the game is the game: Behind the scenes with Andy Murray",
    "description": "the game is the game: challenge 1 video Andy Murray Vs Bajan Road Tennis - The Outtakes! adidas gave Andy Murray one hour to master Bajan Road Tennis, and th...",
    "referenceId": null,
    "date_created": "1398106899",
    "date_modified": "1418181303",
    "tags": "",
    "sourceId": "4",
    "VIDEO_LENGTH": "SHORT",
    "status": "approved",
    "visibility": "1",
    "id": "154389",
    "loginId": "3",
    "entityType": "1",
    "titleTextEncoded": "the-game-is-the-game-Behind-the-scenes-with-Andy-Murray",
    "category": null,
    "duration": 189,
    "settings": [],
    "asset": {
        "author": "adidas",
        "videoId": "48iaZQJHZq0",
        "hookText": "the game is the game: challenge 1 video Andy Murray Vs Bajan Road Tennis - The Outtakes! adidas gave Andy Murray one hour to master Bajan Road Tennis, and th...",
        "thumbnailUrl": "https:\/\/i.ytimg.com\/vi\/48iaZQJHZq0\/maxresdefault.jpg",
        "mediaDuration": "189",
        "hdvFlag": 1,
        "uploadDate": 1322780994,
        "prettyDuration": "03:09"
    },
    "transcripts": null,
    "VV_VI": null,
    "CVV_VI": null,
    "engagement_score": null,
    "conversion_score": null,
    "metrics_statistics": null,
    "tvp_profiles": [
        "32",
        "19",
        "25"
    ],
    "tvp_profiles_manual": null,
    "tvp_profiles_maxscore": 7246.0444
}