{
    "title": "All stars are in | adidas is all in commercial 2011.",
    "description": "This content may trigger seizures for people with photosensitive epilepsy.* Feel the passion with stars such as David Beckham, Derrick Rose, Lionel Messi, a...",
    "referenceId": null,
    "date_created": "1398106920",
    "date_modified": "1418181308",
    "tags": "",
    "sourceId": "4",
    "VIDEO_LENGTH": "SHORT",
    "status": "approved",
    "visibility": "1",
    "id": "154757",
    "loginId": "3",
    "entityType": "1",
    "titleTextEncoded": "All-stars-are-in-adidas-is-all-in-commercial-2011",
    "category": null,
    "duration": 61,
    "settings": [],
    "asset": {
        "author": "adidas",
        "videoId": "J24WDy348ZE",
        "hookText": "This content may trigger seizures for people with photosensitive epilepsy.* Feel the passion with stars such as David Beckham, Derrick Rose, Lionel Messi, a...",
        "thumbnailUrl": "https:\/\/i.ytimg.com\/vi\/J24WDy348ZE\/maxresdefault.jpg",
        "mediaDuration": "61",
        "hdvFlag": 1,
        "uploadDate": 1300232081,
        "prettyDuration": "01:01"
    },
    "transcripts": null,
    "VV_VI": null,
    "CVV_VI": null,
    "engagement_score": null,
    "conversion_score": null,
    "metrics_statistics": null,
    "tvp_profiles": [
        "18"
    ],
    "tvp_profiles_manual": null,
    "tvp_profiles_maxscore": 511.6531
}