{
    "title": "THE GREEN IN STUDIO: DECISIONS",
    "description": "Yet another gem from the Hurley Studios recording session. This song by the green is called \"Decisions\". Enjoy!",
    "referenceId": null,
    "date_created": "1398292496",
    "date_modified": "1418181332",
    "tags": "",
    "sourceId": "4",
    "VIDEO_LENGTH": "LONG",
    "status": "approved",
    "visibility": "1",
    "id": "158615",
    "loginId": "3",
    "entityType": "1",
    "titleTextEncoded": "THE-GREEN-IN-STUDIO-DECISIONS",
    "category": null,
    "duration": 305,
    "settings": [],
    "asset": {
        "author": "Hurley",
        "videoId": "5UAofAq78mM",
        "hookText": "Yet another gem from the Hurley Studios recording session. This song by the green is called \"Decisions\". Enjoy!",
        "thumbnailUrl": "https:\/\/i.ytimg.com\/vi\/5UAofAq78mM\/sddefault.jpg",
        "mediaDuration": "305",
        "hdvFlag": 0,
        "uploadDate": 1322012785,
        "prettyDuration": "05:05"
    },
    "transcripts": null,
    "VV_VI": null,
    "CVV_VI": null,
    "engagement_score": null,
    "conversion_score": null,
    "metrics_statistics": null,
    "tvp_profiles": [
        "34"
    ],
    "tvp_profiles_manual": null,
    "tvp_profiles_maxscore": 5229.359
}