{
    "title": "WHAT THEY RIDE: OWEN WRIGHT",
    "description": "",
    "referenceId": null,
    "date_created": "1398292515",
    "date_modified": "1418181334",
    "tags": "",
    "sourceId": "4",
    "VIDEO_LENGTH": "SHORT",
    "status": "approved",
    "visibility": "1",
    "id": "158798",
    "loginId": "3",
    "entityType": "1",
    "titleTextEncoded": "WHAT-THEY-RIDE-OWEN-WRIGHT",
    "category": null,
    "duration": 49,
    "settings": [],
    "asset": {
        "author": "Hurley",
        "videoId": "4zKs2Y4tTxk",
        "hookText": "",
        "thumbnailUrl": "https:\/\/i.ytimg.com\/vi\/4zKs2Y4tTxk\/maxresdefault.jpg",
        "mediaDuration": "49",
        "hdvFlag": 1,
        "uploadDate": 1285314374,
        "prettyDuration": "00:49"
    },
    "transcripts": null,
    "VV_VI": null,
    "CVV_VI": null,
    "engagement_score": null,
    "conversion_score": null,
    "metrics_statistics": null,
    "tvp_profiles": [
        "31",
        "4"
    ],
    "tvp_profiles_manual": null,
    "tvp_profiles_maxscore": 149.44017
}