{
    "title": "RIP MY SHRED STICK: PT PLEASANT",
    "description": "Another day of RMSS fun in Narragansett, Rhode Island. For photos, results and more info go to hurley.com\/rmss.",
    "referenceId": null,
    "date_created": "1398292487",
    "date_modified": "1418181331",
    "tags": "",
    "sourceId": "4",
    "VIDEO_LENGTH": "SHORT",
    "status": "approved",
    "visibility": "1",
    "id": "158530",
    "loginId": "3",
    "entityType": "1",
    "titleTextEncoded": "RIP-MY-SHRED-STICK-PT-PLEASANT",
    "category": null,
    "duration": 184,
    "settings": [],
    "asset": {
        "author": "Hurley",
        "videoId": "Qp7fKJiJI6E",
        "hookText": "Another day of RMSS fun in Narragansett, Rhode Island. For photos, results and more info go to hurley.com\/rmss.",
        "thumbnailUrl": "https:\/\/i.ytimg.com\/vi\/Qp7fKJiJI6E\/hqdefault.jpg",
        "mediaDuration": "184",
        "hdvFlag": 0,
        "uploadDate": 1341543571,
        "prettyDuration": "03:04"
    },
    "transcripts": null,
    "VV_VI": null,
    "CVV_VI": null,
    "engagement_score": null,
    "conversion_score": null,
    "metrics_statistics": null,
    "tvp_profiles": [
        "9",
        "16"
    ],
    "tvp_profiles_manual": null,
    "tvp_profiles_maxscore": 272.21738
}