{
    "title": "HATV Vegan Ironman",
    "description": "Professional Triathlete Brendan Brazier talks with us how a vegan diet gives him a competitive edge.",
    "referenceId": null,
    "date_created": "1399316178",
    "date_modified": "1418181406",
    "tags": "",
    "sourceId": "4",
    "VIDEO_LENGTH": "SHORT",
    "status": "approved",
    "visibility": "1",
    "id": "165663",
    "loginId": "3",
    "entityType": "1",
    "titleTextEncoded": "HATV-Vegan-Ironman",
    "category": null,
    "duration": 171,
    "settings": [],
    "asset": {
        "author": "Vega",
        "videoId": "_TLvWzlSXmM",
        "hookText": "Professional Triathlete Brendan Brazier talks with us how a vegan diet gives him a competitive edge.",
        "thumbnailUrl": "https:\/\/i.ytimg.com\/vi\/_TLvWzlSXmM\/maxresdefault.jpg",
        "mediaDuration": "171",
        "hdvFlag": 1,
        "uploadDate": 1272006137,
        "prettyDuration": "02:51"
    },
    "transcripts": null,
    "VV_VI": null,
    "CVV_VI": null,
    "engagement_score": null,
    "conversion_score": null,
    "metrics_statistics": null,
    "tvp_profiles": [
        "11"
    ],
    "tvp_profiles_manual": null,
    "tvp_profiles_maxscore": 263.73203
}