{
    "title": "TEAM VEGA - Mud, Sweat & Fears - #5 - Cold Hard Training!",
    "description": "The Vega Team hits the great outdoors for some genuine \"Mudder training\". Follow the group as they prep for the big day. Watch the team as they leap into ice...",
    "referenceId": null,
    "date_created": "1399316166",
    "date_modified": "1418181404",
    "tags": "",
    "sourceId": "4",
    "VIDEO_LENGTH": "SHORT",
    "status": "approved",
    "visibility": "1",
    "id": "165566",
    "loginId": "3",
    "entityType": "1",
    "titleTextEncoded": "TEAM-VEGA-Mud-Sweat-Fears-5-Cold-Hard-Training",
    "category": null,
    "duration": 137,
    "settings": [],
    "asset": {
        "author": "Vega",
        "videoId": "ig35FzPHq_o",
        "hookText": "The Vega Team hits the great outdoors for some genuine \"Mudder training\". Follow the group as they prep for the big day. Watch the team as they leap into ice...",
        "thumbnailUrl": "https:\/\/i.ytimg.com\/vi\/ig35FzPHq_o\/maxresdefault.jpg",
        "mediaDuration": "137",
        "hdvFlag": 1,
        "uploadDate": 1339117636,
        "prettyDuration": "02:17"
    },
    "transcripts": null,
    "VV_VI": null,
    "CVV_VI": null,
    "engagement_score": null,
    "conversion_score": null,
    "metrics_statistics": null,
    "tvp_profiles": [
        "25",
        "31"
    ],
    "tvp_profiles_manual": null,
    "tvp_profiles_maxscore": 615.4873
}