{
    "title": "Clean Eating 101: Get More Bang for Your Buck with Nutrient ",
    "description": "http:\/\/thriveforward.com\/lesson\/clean-eating-101-lesson-2\/ Register for free at ThriveForward.com for supplemental materials, including recipes, downloadable...",
    "referenceId": null,
    "date_created": "1399316162",
    "date_modified": "1418181404",
    "tags": "",
    "sourceId": "4",
    "VIDEO_LENGTH": "SHORT",
    "status": "approved",
    "visibility": "1",
    "id": "165529",
    "loginId": "3",
    "entityType": "1",
    "titleTextEncoded": "Clean-Eating-101-Get-More-Bang-for-Your-Buck-with-Nutrient",
    "category": null,
    "duration": 181,
    "settings": [],
    "asset": {
        "author": "Vega",
        "videoId": "VTWf96JyrMw",
        "hookText": "http:\/\/thriveforward.com\/lesson\/clean-eating-101-lesson-2\/ Register for free at ThriveForward.com for supplemental materials, including recipes, downloadable...",
        "thumbnailUrl": "https:\/\/i.ytimg.com\/vi\/VTWf96JyrMw\/maxresdefault.jpg",
        "mediaDuration": "181",
        "hdvFlag": 1,
        "uploadDate": 1355539174,
        "prettyDuration": "03:01"
    },
    "transcripts": null,
    "VV_VI": null,
    "CVV_VI": null,
    "engagement_score": null,
    "conversion_score": null,
    "metrics_statistics": null,
    "tvp_profiles": [
        "9"
    ],
    "tvp_profiles_manual": null,
    "tvp_profiles_maxscore": 628.601
}