{
    "title": "Extra Credits Announces Extra Remix, Launching April 15!",
    "description": "April 15 marks the debut of Extra Remix, a new show highlighting video game remixes and the people who make them. This weekly show will air every Tuesday! Su...",
    "referenceId": null,
    "date_created": "1406055182",
    "date_modified": "1418181771",
    "tags": "",
    "sourceId": "4",
    "VIDEO_LENGTH": "SHORT",
    "status": "approved",
    "visibility": "1",
    "id": "191612",
    "loginId": "3",
    "entityType": "1",
    "titleTextEncoded": "Extra-Credits-Announces-Extra-Remix-Launching-April-15",
    "category": null,
    "duration": 135,
    "settings": [],
    "asset": {
        "author": "Extra Credits",
        "videoId": "XxkPT61aXQU",
        "hookText": "April 15 marks the debut of Extra Remix, a new show highlighting video game remixes and the people who make them. This weekly show will air every Tuesday! Su...",
        "thumbnailUrl": "https:\/\/i.ytimg.com\/vi\/XxkPT61aXQU\/maxresdefault.jpg",
        "mediaDuration": "135",
        "hdvFlag": 1,
        "uploadDate": 1397352233,
        "prettyDuration": "02:15"
    },
    "transcripts": null,
    "VV_VI": null,
    "CVV_VI": null,
    "engagement_score": null,
    "conversion_score": null,
    "metrics_statistics": null,
    "tvp_profiles": [
        "9",
        "26"
    ],
    "tvp_profiles_manual": null,
    "tvp_profiles_maxscore": 322.52942
}