{
    "title": "Q&A #3 with Dan and James (January 1st, 2014)",
    "description": "Dan and James answer your questions! In the same room, for once!",
    "referenceId": null,
    "date_created": "1406055184",
    "date_modified": "1418181772",
    "tags": "",
    "sourceId": "4",
    "VIDEO_LENGTH": "LONG",
    "status": "approved",
    "visibility": "1",
    "id": "191632",
    "loginId": "3",
    "entityType": "1",
    "titleTextEncoded": "Q-A-3-with-Dan-and-James-January-1st-2014",
    "category": null,
    "duration": 4507,
    "settings": [],
    "asset": {
        "author": "Extra Credits",
        "videoId": "YG_V0Q_MB5Q",
        "hookText": "Dan and James answer your questions! In the same room, for once!",
        "thumbnailUrl": "https:\/\/i.ytimg.com\/vi\/YG_V0Q_MB5Q\/maxresdefault.jpg",
        "mediaDuration": "4507",
        "hdvFlag": 1,
        "uploadDate": 1388790003,
        "prettyDuration": "01:15:07"
    },
    "transcripts": null,
    "VV_VI": null,
    "CVV_VI": null,
    "engagement_score": null,
    "conversion_score": null,
    "metrics_statistics": null,
    "tvp_profiles": [
        "2"
    ],
    "tvp_profiles_manual": null,
    "tvp_profiles_maxscore": 2887.3076
}