{
    "title": "Government Taking Your \"Inactive\" Money | The Daily Briefing",
    "description": "The government taking your money from what they deem are \"inactive\" bank accounts? Glenn Beck and his staff discuss what's happening.",
    "referenceId": null,
    "date_created": "1408046542",
    "date_modified": "1418181877",
    "tags": "",
    "sourceId": "4",
    "VIDEO_LENGTH": "SHORT",
    "status": "approved",
    "visibility": "1",
    "id": "198189",
    "loginId": "3",
    "entityType": "1",
    "titleTextEncoded": "Government-Taking-Your-Inactive-Money-The-Daily-Briefing",
    "category": null,
    "duration": 234,
    "settings": [],
    "asset": {
        "author": "TheBlaze",
        "videoId": "PvWtl_j-5c4",
        "hookText": "The government taking your money from what they deem are \"inactive\" bank accounts? Glenn Beck and his staff discuss what's happening.",
        "thumbnailUrl": "https:\/\/i.ytimg.com\/vi\/PvWtl_j-5c4\/maxresdefault.jpg",
        "mediaDuration": "234",
        "hdvFlag": 1,
        "uploadDate": 1403060444,
        "prettyDuration": "03:54"
    },
    "transcripts": null,
    "VV_VI": null,
    "CVV_VI": null,
    "engagement_score": null,
    "conversion_score": null,
    "metrics_statistics": null,
    "tvp_profiles": [
        "20"
    ],
    "tvp_profiles_manual": null,
    "tvp_profiles_maxscore": 4947.1094
}