{
    "title": "U.S. Role in Venezuela? | Marco Rubio on \"Real News\"",
    "description": "Senator Marco Rubio joins Real News to discuss the ongoing violence in Venezuela. As the Venezuelan police and National Guard continue efforts to mop up prot...",
    "referenceId": null,
    "date_created": "1408046563",
    "date_modified": "1418181881",
    "tags": "",
    "sourceId": "4",
    "VIDEO_LENGTH": "SHORT",
    "status": "approved",
    "visibility": "1",
    "id": "198416",
    "loginId": "3",
    "entityType": "1",
    "titleTextEncoded": "U-S-Role-in-Venezuela-Marco-Rubio-on-Real-News",
    "category": null,
    "duration": 161,
    "settings": [],
    "asset": {
        "author": "TheBlaze",
        "videoId": "bVoAFNqZ3ig",
        "hookText": "Senator Marco Rubio joins Real News to discuss the ongoing violence in Venezuela. As the Venezuelan police and National Guard continue efforts to mop up prot...",
        "thumbnailUrl": "https:\/\/i.ytimg.com\/vi\/bVoAFNqZ3ig\/maxresdefault.jpg",
        "mediaDuration": "161",
        "hdvFlag": 0,
        "uploadDate": 1396485130,
        "prettyDuration": "02:41"
    },
    "transcripts": null,
    "VV_VI": null,
    "CVV_VI": null,
    "engagement_score": null,
    "conversion_score": null,
    "metrics_statistics": null,
    "tvp_profiles": [
        "33"
    ],
    "tvp_profiles_manual": null,
    "tvp_profiles_maxscore": 310.3811
}