{
    "title": "China Buying Golf Courses and Jumbo Jets | The Daily Briefin",
    "description": "Why is China buying American golf courses and jumbo jets? Glenn Beck and his radio producer Jeff Fisher discuss.",
    "referenceId": null,
    "date_created": "1408046542",
    "date_modified": "1418181877",
    "tags": "",
    "sourceId": "4",
    "VIDEO_LENGTH": "SHORT",
    "status": "approved",
    "visibility": "1",
    "id": "198185",
    "loginId": "3",
    "entityType": "1",
    "titleTextEncoded": "China-Buying-Golf-Courses-and-Jumbo-Jets-The-Daily-Briefin",
    "category": null,
    "duration": 217,
    "settings": [],
    "asset": {
        "author": "TheBlaze",
        "videoId": "Z2cZbQPoy2Y",
        "hookText": "Why is China buying American golf courses and jumbo jets? Glenn Beck and his radio producer Jeff Fisher discuss.",
        "thumbnailUrl": "https:\/\/i.ytimg.com\/vi\/Z2cZbQPoy2Y\/maxresdefault.jpg",
        "mediaDuration": "217",
        "hdvFlag": 1,
        "uploadDate": 1403145714,
        "prettyDuration": "03:37"
    },
    "transcripts": null,
    "VV_VI": null,
    "CVV_VI": null,
    "engagement_score": null,
    "conversion_score": null,
    "metrics_statistics": null,
    "tvp_profiles": [
        "9",
        "25"
    ],
    "tvp_profiles_manual": null,
    "tvp_profiles_maxscore": 207.79742
}