{
    "title": "Glassholes, Emoticons, Kid in Claw Machine | What We Didn't ",
    "description": "Laurie's take on an outrageous fine for not paying for a soda refill, a kid gets stuck in a claw machine, Google Glass sells out, and Emoticons are 360 years...",
    "referenceId": null,
    "date_created": "1408046557",
    "date_modified": "1418181880",
    "tags": "",
    "sourceId": "4",
    "VIDEO_LENGTH": "LONG",
    "status": "approved",
    "visibility": "1",
    "id": "198346",
    "loginId": "3",
    "entityType": "1",
    "titleTextEncoded": "Glassholes-Emoticons-Kid-in-Claw-Machine-What-We-Didn-t",
    "category": null,
    "duration": 275,
    "settings": [],
    "asset": {
        "author": "TheBlaze",
        "videoId": "m6XH1WkcQ4Y",
        "hookText": "Laurie's take on an outrageous fine for not paying for a soda refill, a kid gets stuck in a claw machine, Google Glass sells out, and Emoticons are 360 years...",
        "thumbnailUrl": "https:\/\/i.ytimg.com\/vi\/m6XH1WkcQ4Y\/maxresdefault.jpg",
        "mediaDuration": "275",
        "hdvFlag": 1,
        "uploadDate": 1397874059,
        "prettyDuration": "04:35"
    },
    "transcripts": null,
    "VV_VI": null,
    "CVV_VI": null,
    "engagement_score": null,
    "conversion_score": null,
    "metrics_statistics": null,
    "tvp_profiles": [
        "14"
    ],
    "tvp_profiles_manual": null,
    "tvp_profiles_maxscore": 413.8425
}