{
    "title": "Six Figures With No College Degree | The Daily Briefing: 7.1",
    "description": "Glenn Beck and his staff discuss the jobs available where you can make six-figures...without a college degree. See more: http:\/\/TheBlaze.com\/TV.",
    "referenceId": null,
    "date_created": "1408046538",
    "date_modified": "1418181877",
    "tags": "",
    "sourceId": "4",
    "VIDEO_LENGTH": "SHORT",
    "status": "approved",
    "visibility": "1",
    "id": "198135",
    "loginId": "3",
    "entityType": "1",
    "titleTextEncoded": "Six-Figures-With-No-College-Degree-The-Daily-Briefing-7-1",
    "category": null,
    "duration": 234,
    "settings": [],
    "asset": {
        "author": "TheBlaze",
        "videoId": "ASmj89Nmih0",
        "hookText": "Glenn Beck and his staff discuss the jobs available where you can make six-figures...without a college degree. See more: http:\/\/TheBlaze.com\/TV.",
        "thumbnailUrl": "https:\/\/i.ytimg.com\/vi\/ASmj89Nmih0\/maxresdefault.jpg",
        "mediaDuration": "234",
        "hdvFlag": 1,
        "uploadDate": 1405477744,
        "prettyDuration": "03:54"
    },
    "transcripts": null,
    "VV_VI": null,
    "CVV_VI": null,
    "engagement_score": null,
    "conversion_score": null,
    "metrics_statistics": null,
    "tvp_profiles": [
        "12",
        "14",
        "11"
    ],
    "tvp_profiles_manual": null,
    "tvp_profiles_maxscore": 450.0077
}