{
    "title": "American Jihadis | The Hotlist",
    "description": "Westerners leaving home to join extremists abroad? Amy Holmes brings you the unbelievable stories of Americans joining Muslim Jihads. Let us know what you think of these stories and how the...",
    "referenceId": null,
    "date_created": "1408046532",
    "date_modified": "1418181875",
    "tags": "",
    "sourceId": "4",
    "VIDEO_LENGTH": "SHORT",
    "status": "approved",
    "visibility": "1",
    "id": "198060",
    "loginId": "3",
    "entityType": "1",
    "titleTextEncoded": "American-Jihadis-The-Hotlist",
    "category": null,
    "duration": 129,
    "settings": [],
    "asset": {
        "author": "TheBlaze",
        "videoId": "vi36pxI_Ij0",
        "hookText": "Westerners leaving home to join extremists abroad? Amy Holmes brings you the unbelievable stories of Americans joining Muslim Jihads. Let us know what you think of these stories and how the...",
        "thumbnailUrl": "https:\/\/i.ytimg.com\/vi\/vi36pxI_Ij0\/maxresdefault.jpg",
        "mediaDuration": "129",
        "hdvFlag": 1,
        "uploadDate": 1407871803,
        "prettyDuration": "02:09"
    },
    "transcripts": null,
    "VV_VI": null,
    "CVV_VI": null,
    "engagement_score": null,
    "conversion_score": null,
    "metrics_statistics": null,
    "tvp_profiles": [
        "14",
        "18",
        "11"
    ],
    "tvp_profiles_manual": null,
    "tvp_profiles_maxscore": 456.80878
}