{
    "title": "2012 Rossignol Experience 78 Skis Review",
    "description": "http:\/\/www.skis.com Review for the 2012 Rossignol Experience 78 Skis",
    "referenceId": null,
    "date_created": "1411361305",
    "date_modified": "1418182026",
    "tags": "",
    "sourceId": "4",
    "VIDEO_LENGTH": "SHORT",
    "status": "approved",
    "visibility": "1",
    "id": "3767422",
    "loginId": "3",
    "entityType": "1",
    "titleTextEncoded": "2012-Rossignol-Experience-78-Skis-Review",
    "category": null,
    "duration": 30,
    "settings": [],
    "asset": {
        "author": "skisdotcom",
        "videoId": "aVbk_-_neh8",
        "hookText": "http:\/\/www.skis.com Review for the 2012 Rossignol Experience 78 Skis",
        "thumbnailUrl": "https:\/\/i.ytimg.com\/vi\/aVbk_-_neh8\/sddefault.jpg",
        "mediaDuration": "30",
        "hdvFlag": 0,
        "uploadDate": 1314665315,
        "prettyDuration": "00:30"
    },
    "transcripts": null,
    "VV_VI": null,
    "CVV_VI": null,
    "engagement_score": null,
    "conversion_score": null,
    "metrics_statistics": null,
    "tvp_profiles": [
        "14",
        "7"
    ],
    "tvp_profiles_manual": null,
    "tvp_profiles_maxscore": 145.02597
}