{
    "title": "Bluefly.com's Closet Confession - Jane Larkworthy",
    "description": "Ever wonder about the private lives of top magazine editors and directors? Well, your curiosity ends here! Take an exclusive look into W Magazine's Beauty Di...",
    "referenceId": null,
    "date_created": "1423255308",
    "date_modified": "1423255308",
    "tags": "",
    "sourceId": "4",
    "VIDEO_LENGTH": "SHORT",
    "status": "approved",
    "visibility": "1",
    "id": "3817008",
    "loginId": "3",
    "entityType": "1",
    "titleTextEncoded": "Bluefly-com-s-Closet-Confession-Jane-Larkworthy",
    "category": null,
    "duration": 228,
    "settings": null,
    "asset": {
        "author": "Bluefly",
        "hdvFlag": 1,
        "hookText": "Ever wonder about the private lives of top magazine editors and directors? Well, your curiosity ends here! Take an exclusive look into W Magazine's Beauty Di...",
        "tags": "",
        "thumbnailUrl": "https:\/\/i.ytimg.com\/vi\/mHtQrRS5doo\/sddefault.jpg",
        "uploadDate": 1376668720,
        "videoId": "mHtQrRS5doo",
        "mediaDuration": "228",
        "prettyDuration": "03:48"
    },
    "transcripts": null,
    "VV_VI": null,
    "CVV_VI": null,
    "engagement_score": null,
    "conversion_score": null,
    "metrics_statistics": null,
    "tvp_profiles": [
        "12",
        "11"
    ],
    "tvp_profiles_manual": null,
    "tvp_profiles_maxscore": 241.17004
}